jabbbar/__init__.py
jabbbar/bucket.py
jabbbar/jabbbar.py
jabbbar/project.py
jabbbar/shot.py
jabbbar/team.py
jabbbar/user.py
jabbbar/tests/__init__.py
jabbbar/tests/credentials.example.py
jabbbar/tests/credentials.py
jabbbar/tests/test_bucket.py
jabbbar/tests/test_project.py
jabbbar/tests/test_shot.py
jabbbar/tests/test_team.py
jabbbar/tests/test_teams.py
jabbbar/tests/test_user.py
jabbbar-0.3.0.dist-info/DESCRIPTION.rst
jabbbar-0.3.0.dist-info/METADATA
jabbbar-0.3.0.dist-info/RECORD
jabbbar-0.3.0.dist-info/WHEEL
jabbbar-0.3.0.dist-info/metadata.json
jabbbar-0.3.0.dist-info/top_level.txt
