Metadata-Version: 2.0
Name: jabbbar
Version: 0.3.0
Summary: A python 3 wrapper for the Dribbble API
Home-page: https://github.com/zabanaa/jabbbar
Author: Karim Cheurfi (Zabana)
Author-email: karim.cheurfi@gmail.com
License: WTFPL
Keywords: dribbble,api,http,wrapper,jabbbar
Platform: UNKNOWN
Classifier: Development Status :: 4 - Beta
Classifier: Intended Audience :: Developers
Classifier: Natural Language :: English
Classifier: Operating System :: OS Independent
Classifier: Programming Language :: Python
Classifier: Programming Language :: Python :: 3.3
Classifier: Programming Language :: Python :: 3.4
Classifier: Programming Language :: Python :: 3.5
Requires-Dist: requests
